setup.cfg
setup.py
webpyutils/__init__.py
webpyutils/api.py
webpyutils.egg-info/PKG-INFO
webpyutils.egg-info/SOURCES.txt
webpyutils.egg-info/dependency_links.txt
webpyutils.egg-info/requires.txt
webpyutils.egg-info/top_level.txt