Metadata-Version: 1.1
Name: webpyutils
Version: 0.1
Summary: web.py utilities to build quick RESTful API Services
Home-page: https://github.com/jvy1106/webpyutils
Author: Jesse V. Yen
Author-email: jesse@jads.com
License: UNKNOWN
Download-URL: https://github.com/jvy1106/webpyutils/tarball/0.1
Keywords: api,restful,server
Platform: UNKNOWN
